{"cc8fe58b-7ae7-440d-8fcf-9cb840e53e94":{"answers":["expectations"],"createdTimestamp":"2021-09-29T01:29:47.791Z"},"0df3e0ea-2945-45d0-b421-98d01c4c44c0":{"answers":["competitive academics"],"createdTimestamp":"2021-09-29T01:29:49.701Z"},"962d862a-b098-4283-8f12-7abed1374225":{"answers":["Blind trust in statistics "],"createdTimestamp":"2021-09-29T01:29:57.478Z"},"9adedfde-e377-4085-8b0e-700afedf4c4e":{"answers":["The value of categorization and means. "],"createdTimestamp":"2021-09-29T01:30:16.840Z"},"c5d182d3-c4bd-4f92-93fd-119afedca697":{"answers":["The value of categorization and means. "],"createdTimestamp":"2021-09-29T01:30:17.504Z"},"0c2ea94a-5fed-4166-b906-77f3f3dfe24d":{"answers":["everything is bigger and smaller than it acutally seems to be"],"createdTimestamp":"2021-09-29T01:30:22.593Z"},"f0b37e42-556c-48d9-85dc-f286df7b0422":{"answers":["Colonialism"],"createdTimestamp":"2021-09-29T01:30:25.164Z"},"87c86f10-e8df-44ca-bea2-2893fd547400":{"answers":["Assumptions "],"createdTimestamp":"2021-09-29T01:30:28.973Z"},"f8109c64-2ca3-4188-bbf9-500a4d53d662":{"answers":["How to start a course--this way is better!"],"createdTimestamp":"2021-09-29T01:30:29.566Z"},"bdfeac8d-27f1-4a56-9c9d-f819e126dfe2":{"answers":["Subconscious categorisation "],"createdTimestamp":"2021-09-29T01:30:33.415Z"},"abb7eb55-d288-450c-a708-b85d38f87a3c":{"answers":["Being the perfect student"],"createdTimestamp":"2021-09-29T01:30:35.691Z"},"7c6bd49a-6220-4bdd-9daa-f1b908d0251e":{"answers":["academics "],"createdTimestamp":"2021-09-29T01:30:36.368Z"},"b2371c82-3030-4d85-96fa-52a07b22833b":{"answers":["The ontology of humanity"],"createdTimestamp":"2021-09-29T01:30:41.188Z"},"c18fe668-f2ff-4daa-a1fd-bd99376a80f4":{"answers":["to question beliefs and be open to understand the answers "],"createdTimestamp":"2021-09-29T01:30:45.597Z"},"84f7cc3d-32cc-4515-a9b2-633fc19822a9":{"answers":["Society operates on a surface level"],"createdTimestamp":"2021-09-29T01:30:54.363Z"},"715190ad-63a0-4df8-a4ad-64ef132e51bb":{"answers":["What success can look like "],"createdTimestamp":"2021-09-29T01:30:58.136Z"},"ffafa709-8e38-4c02-bc03-172e2990170b":{"answers":["Subconscious categorisation "],"createdTimestamp":"2021-09-29T01:31:00.293Z"},"32cad55a-f838-448f-9cd4-a65b8ecd30a2":{"answers":["Subconscious categorisation "],"createdTimestamp":"2021-09-29T01:31:00.882Z"},"82c24c2b-509d-4e09-be24-6d3583b9e2af":{"answers":["I am at a better position when it comes to ‘disability’ // society disables pple"],"createdTimestamp":"2021-09-29T01:31:01.331Z"},"eb467c9d-0637-444f-9991-2362aa6e65f6":{"answers":["I am at a better position when it comes to ‘disability’ // society disables pple"],"createdTimestamp":"2021-09-29T01:31:02.728Z"},"eae7adc7-4b24-4760-8d0f-ab90d1e17047":{"answers":["Trying to 'fix' things"],"createdTimestamp":"2021-09-29T01:31:10.836Z"},"10e1351b-8eee-4c76-8955-51fbf524c4f4":{"answers":["sleep"],"createdTimestamp":"2021-09-29T01:31:15.689Z"},"a642ba46-5182-4ff5-86a5-8c183c57570d":{"answers":["a lot"],"createdTimestamp":"2021-09-29T01:31:17.207Z"},"6c4a6bb2-263a-4330-9673-f41942132c35":{"answers":["the idea of perfection"],"createdTimestamp":"2021-09-29T01:31:20.781Z"},"def9a242-0510-428b-8c97-a4f1620ebf65":{"answers":["my biases"],"createdTimestamp":"2021-09-29T01:31:26.769Z"},"912a56da-5ac2-437c-b66d-96f155e03c75":{"answers":["the very concept of disability "],"createdTimestamp":"2021-09-29T01:31:29.604Z"},"507dd2a1-32e1-49a9-a872-b87d6b0abbc6":{"answers":["necessity of pronoun declarations"],"createdTimestamp":"2021-09-29T01:31:31.718Z"},"63d989df-1dbe-4bfc-b818-c96d7f974efe":{"answers":["More confidence"],"createdTimestamp":"2021-09-29T01:31:33.935Z"},"94692158-914b-4232-8555-0891d44b5046":{"answers":["rules"],"createdTimestamp":"2021-09-29T01:31:51.352Z"},"c33c61be-9898-4bdd-add8-da84ec29107c":{"answers":["not to look from a lens of differences among individuals"],"createdTimestamp":"2021-09-29T01:32:56.220Z"},"1706bd4b-f80d-4806-9ea1-8afe7b13124c":{"answers":["Control the things very well"],"createdTimestamp":"2021-09-29T01:33:28.035Z"}}
